wasure/__init__.py
wasure/__main__.py
wasure/wasure.py
wasure/benchmarks/.DS_Store
wasure/benchmarks/coremark/benchmarks.json
wasure/benchmarks/coremark/coremark-1000.wasm
wasure/benchmarks/coremark/coremark-11000.wasm
wasure/benchmarks/coremark/coremark-5000.wasm
wasure/benchmarks/coremark/coremark.wasm
wasure/benchmarks/cpu-benchmark-py/benchmarks.json
wasure/benchmarks/cpu-benchmark-py/cpu-benchmark.wasm
wasure/benchmarks/dhrystone/benchmarks.json
wasure/benchmarks/dhrystone/dhrystone100M.wasm
wasure/benchmarks/dhrystone/dhrystone10M.wasm
wasure/benchmarks/dhrystone/dhrystone1B.wasm
wasure/benchmarks/dhrystone/dhrystone1M.wasm
wasure/benchmarks/dhrystone/dhrystoneMAX.wasm
wasure/benchmarks/dummy/benchmarks.json
wasure/benchmarks/dummy/dummy.wasm
wasure/benchmarks/dummy/dummy.wat
wasure/benchmarks/dummy/param.wasm
wasure/benchmarks/helloworld/benchmarks.json
wasure/benchmarks/helloworld/helloworld.wasm
wasure/benchmarks/kotlin-prime/benchmarks.json
wasure/benchmarks/kotlin-prime/kotlin-prime-100K.wasm
wasure/benchmarks/kotlin-prime/kotlin-prime-10K.wasm
wasure/benchmarks/kotlin-prime/kotlin-prime-1K.wasm
wasure/benchmarks/kotlin-prime/kotlin-prime-1M.wasm
wasure/benchmarks/libsodium/.DS_Store
wasure/benchmarks/libsodium/aead_chacha20poly1305.wasm
wasure/benchmarks/libsodium/aead_chacha20poly13052.wasm
wasure/benchmarks/libsodium/aead_xchacha20poly1305.wasm
wasure/benchmarks/libsodium/auth.wasm
wasure/benchmarks/libsodium/auth2.wasm
wasure/benchmarks/libsodium/auth3.wasm
wasure/benchmarks/libsodium/auth5.wasm
wasure/benchmarks/libsodium/auth6.wasm
wasure/benchmarks/libsodium/auth7.wasm
wasure/benchmarks/libsodium/benchmarks.json
wasure/benchmarks/libsodium/box.wasm
wasure/benchmarks/libsodium/box2.wasm
wasure/benchmarks/libsodium/box7.wasm
wasure/benchmarks/libsodium/box8.wasm
wasure/benchmarks/libsodium/box_easy.wasm
wasure/benchmarks/libsodium/box_easy2.wasm
wasure/benchmarks/libsodium/box_seal.wasm
wasure/benchmarks/libsodium/box_seed.wasm
wasure-0.9.dist-info/licenses/LICENSE
wasure-0.9.dist-info/METADATA
wasure-0.9.dist-info/WHEEL
wasure-0.9.dist-info/entry_points.txt
wasure-0.9.dist-info/top_level.txt
wasure-0.9.dist-info/RECORD
