Metadata-Version: 2.4
Name: wasure
Version: 0.9
Summary: A WebAssembly benchmarking suite for precise performance measurement
Home-page: https://github.com/r-carissimi/wasure
Author: Riccardo Carissimi
License: GPL v.3
Project-URL: Bug Tracker, https://github.com/r-carissimi/wasure/issues
Keywords: wasure,webassembly,wasm,benchmarking,performance,measurement
Classifier: Environment :: Console
Classifier: Operating System :: MacOS
Classifier: Operating System :: POSIX :: Linux
Classifier: Programming Language :: Python
Classifier: Programming Language :: Python :: 3
Classifier: Topic :: System :: Benchmark
Requires-Python: >=3.8
License-File: LICENSE
Requires-Dist: matplotlib
Requires-Dist: psutil
Dynamic: license-file
